[
  {
    "obj": {
      "start_x": 4.35,
      "start_y": 3.25,
      "start_z": 3.27,
      "scale_x": 0.05,
      "scale_y": 0.05,
      "scale_z": 0.58
    }
  },
  {
    "obj": {
      "start_x": 1.55,
      "start_y": 1.85,
      "start_z": 2.55,
      "scale_x": 0.05,
      "scale_y": 0.05,
      "scale_z": 1.3
    }
  },
  {
    "obj": {
      "start_x": 3.85,
      "start_y": 3.85,
      "start_z": 3.85,
      "scale_x": 0.05,
      "scale_y": 0.25,
      "scale_z": 0.05
    }
  },
  {
    "obj": {
      "start_x": 3.85,
      "start_y": 4.1,
      "start_z": 3.85,
      "scale_x": 0.05,
      "scale_y": 0.45,
      "scale_z": 0.05
    }
  },
  {
    "obj": {
      "start_x": 3.9,
      "start_y": 4.5,
      "start_z": 3.85,
      "scale_x": 0.5,
      "scale_y": 0.05,
      "scale_z": 0.05
    }
  },
  {
    "obj": {
      "start_x": 4.35,
      "start_y": 3.25,
      "start_z": 3.85,
      "scale_x": 0.05,
      "scale_y": 1.3,
      "scale_z": 0.05
    }
  },
  {
    "obj": {
      "start_x": 1.55,
      "start_y": 4.5,
      "start_z": 3.85,
      "scale_x": 2.3,
      "scale_y": 0.05,
      "scale_z": 0.05
    }
  },
  {
    "obj": {
      "start_x": 1.55,
      "start_y": 1.85,
      "start_z": 3.85,
      "scale_x": 0.05,
      "scale_y": 2.7,
      "scale_z": 0.05
    }
  },
  {
    "obj": {
      "start_x": 2.97,
      "start_y": 3.27,
      "start_z": 3.27,
      "scale_x": 0.37,
      "scale_y": 0.08,
      "scale_z": 0.08
    }
  },
  {
    "obj": {
      "start_x": 2.97,
      "start_y": 2.92,
      "start_z": 3.27,
      "scale_x": 0.08,
      "scale_y": 0.37,
      "scale_z": 0.08
    }
  },
  {
    "obj": {
      "start_x": 3.02,
      "start_y": 2.92,
      "start_z": 3.27,
      "scale_x": 1.4,
      "scale_y": 0.08,
      "scale_z": 0.08
    }
  },
  {
    "obj": {
      "start_x": 4.35,
      "start_y": 2.92,
      "start_z": 3.27,
      "scale_x": 0.05,
      "scale_y": 0.4,
      "scale_z": 0.08
    }
  },
  {
    "obj": {
      "start_x": 1.55,
      "start_y": 2.92,
      "start_z": 3.27,
      "scale_x": 1.55,
      "scale_y": 0.08,
      "scale_z": 0.08
    }
  },
  {
    "obj": {
      "start_x": 1.55,
      "start_y": 1.85,
      "start_z": 3.27,
      "scale_x": 0.05,
      "scale_y": 1.15,
      "scale_z": 0.08
    }
  },
  {
    "obj": {
      "start_x": 1.95,
      "start_y": 2.05,
      "start_z": 2.55,
      "scale_x": 0.08,
      "scale_y": 0.28,
      "scale_z": 0.08
    }
  },
  {
    "obj": {
      "start_x": 1.95,
      "start_y": 1.95,
      "start_z": 2.55,
      "scale_x": 0.08,
      "scale_y": 0.32,
      "scale_z": 0.08
    }
  },
  {
    "obj": {
      "start_x": 1.9,
      "start_y": 1.95,
      "start_z": 2.55,
      "scale_x": 0.37,
      "scale_y": 0.08,
      "scale_z": 0.08
    }
  },
  {
    "obj": {
      "start_x": 2.2,
      "start_y": 2.0,
      "start_z": 2.55,
      "scale_x": 0.08,
      "scale_y": 0.47,
      "scale_z": 0.08
    }
  },
  {
    "obj": {
      "start_x": 1.55,
      "start_y": 2.4,
      "start_z": 2.55,
      "scale_x": 0.67,
      "scale_y": 0.08,
      "scale_z": 0.08
    }
  },
  {
    "obj": {
      "start_x": 1.55,
      "start_y": 1.85,
      "start_z": 2.55,
      "scale_x": 0.05,
      "scale_y": 0.62,
      "scale_z": 0.08
    }
  }
]